deepC/__init__.py
deepC/_dnnc.so
deepC/dnnc.py
deepC/op_gen.py
deepC/setup.py
deepC/tensor_interface_helper.py
deepC/scripts/onnx2cpp.py
deepC/scripts/onnx2exe.py
deepC/scripts/read_onnx.py
deepC-0.1.dist-info/LICENSE
deepC-0.1.dist-info/METADATA
deepC-0.1.dist-info/WHEEL
deepC-0.1.dist-info/entry_points.txt
deepC-0.1.dist-info/top_level.txt
deepC-0.1.dist-info/RECORD
