Metadata-Version: 2.1
Name: deepC
Version: 0.1
Summary: DeepC: Deep Neural Network Compiler
Home-page: https://github.com/ai-techsystems/dnnCompiler
Author: Rohit Sharma et. al.
Author-email: rohit@find-domain-name-on-github.com
License: UNKNOWN
Platform: UNKNOWN
Classifier: Development Status :: 2 - Pre-Alpha
Classifier: Programming Language :: Python :: 3
Classifier: Programming Language :: C++
Classifier: License :: OSI Approved :: MIT License
Classifier: Operating System :: POSIX :: Linux
Classifier: Operating System :: Unix
Requires-Python: >=3.5
Requires-Dist: numpy
Requires-Dist: onnx
